Metadata-Version: 1.1
Name: scieloscopus
Version: 1.0.0
Summary: Library to delivery Scopus and Scimago indicators of SciELO Journals
Home-page: https://github.com/scieloorg/scieloscopus
Author: Ednilson Gesseff
Author-email: ednilson.gesseff@scielo.org
License: BSD 2-clause "Simplified" License
Keywords: scielo scopus scimago cwts journal bibliometry bibliometric indicators data sciences
Platform: UNKNOWN
Classifier: Development Status :: 5 - Production/Stable
Classifier: Intended Audience :: Developers
Classifier: Intended Audience :: Science/Research
Classifier: Natural Language :: English
Classifier: Operating System :: Unix
Classifier: Operating System :: MacOS
Classifier: Programming Language :: Python :: 3.5
Classifier: Programming Language :: Python :: 2.7
Classifier: Topic :: Software Development :: Libraries :: Python Modules
